ilogger/__init__.py
ilogger/ilogger.py
test/__init__.py
test/test_ilogger.py
package_ilogger_Nouvelle_version-1.1.0.dist-info/METADATA
package_ilogger_Nouvelle_version-1.1.0.dist-info/WHEEL
package_ilogger_Nouvelle_version-1.1.0.dist-info/entry_points.txt
package_ilogger_Nouvelle_version-1.1.0.dist-info/top_level.txt
package_ilogger_Nouvelle_version-1.1.0.dist-info/RECORD
